[{"id":"9cb4a51b.8e70b8","type":"tab","label":"Flow 2","disabled":false,"info":""},{"id":"c901233d.196f3","type":"debug","z":"9cb4a51b.8e70b8","name":"","active":true,"tosidebar":true,"console":false,"tostatus":false,"complete":"payload","targetType":"msg","statusVal":"","statusType":"auto","x":570,"y":120,"wires":[]},{"id":"65928c39.7dca14","type":"function","z":"9cb4a51b.8e70b8","name":"slot","func":"global.set('s',msg.payload.d.slot)\nreturn{payload:msg.payload.d.slot}\n","outputs":1,"noerr":0,"initialize":"","finalize":"","libs":[],"x":350,"y":160,"wires":[["c901233d.196f3","da8b1bae.afeaa8"]]},{"id":"685cab8a.364904","type":"function","z":"9cb4a51b.8e70b8","name":"count","func":"global.set('c',msg.payload.d.count)\nreturn{payload:msg.payload.d.count}","outputs":1,"noerr":0,"initialize":"","finalize":"","libs":[],"x":310,"y":260,"wires":[["e2b0bca0.ebfaf","c901233d.196f3"]]},{"id":"cf0bc711.fb7008","type":"cloudant out","z":"9cb4a51b.8e70b8","name":"","cloudant":"","database":"car_parking","service":"node-red-uadru-2021--cloudant-1620999329329-43626","payonly":false,"operation":"insert","x":290,"y":340,"wires":[]},{"id":"5e70274b.40e128","type":"function","z":"9cb4a51b.8e70b8","name":"","func":"msg.payload={\"slot\":global.get('s'),\"count\":global.get('c')}\nreturn msg;","outputs":1,"noerr":0,"initialize":"","finalize":"","libs":[],"x":420,"y":480,"wires":[["f78e3fcc.a737d"]]},{"id":"b0e23d97.d86e2","type":"ibmiot in","z":"9cb4a51b.8e70b8","authentication":"apiKey","apiKey":"251dac8b.e40ad4","inputType":"evt","logicalInterface":"","ruleId":"","deviceId":"1001","applicationId":"","deviceType":"iotdevice","eventType":"+","commandType":"","format":"json","name":"IBM IoT","service":"registered","allDevices":"","allApplications":"","allDeviceTypes":"","allLogicalInterfaces":"","allEvents":true,"allCommands":"","allFormats":"","qos":0,"x":90,"y":220,"wires":[["65928c39.7dca14","685cab8a.364904","cf0bc711.fb7008","c901233d.196f3"]]},{"id":"da8b1bae.afeaa8","type":"ui_gauge","z":"9cb4a51b.8e70b8","name":"slot","group":"e94b4e9a.62a15","order":0,"width":0,"height":0,"gtype":"gage","title":"slot","label":"c","format":"{{value}}","min":0,"max":"100","colors":["#a700b3","#e6e600","#ca3838"],"seg1":"","seg2":"","x":530,"y":240,"wires":[]},{"id":"e2b0bca0.ebfaf","type":"ui_chart","z":"9cb4a51b.8e70b8","name":"count","group":"e94b4e9a.62a15","order":1,"width":0,"height":0,"label":"count","chartType":"line","legend":"false","xformat":"HH:mm:ss","interpolate":"linear","nodata":"","dot":false,"ymin":"0","ymax":"100","removeOlder":1,"removeOlderPoints":"","removeOlderUnit":"3600","cutout":0,"useOneColor":false,"useUTC":false,"colors":["#1f77b4","#aec7e8","#ff7f0e","#2ca02c","#98df8a","#d62728","#ff9896","#9467bd","#c5b0d5"],"outputs":1,"useDifferentColor":false,"x":510,"y":320,"wires":[[]]},{"id":"90b6dc30.c3214","type":"http in","z":"9cb4a51b.8e70b8","name":"carparking","url":"/carparking","method":"get","upload":false,"swaggerDoc":"","x":180,"y":480,"wires":[["5e70274b.40e128"]]},{"id":"f78e3fcc.a737d","type":"http response","z":"9cb4a51b.8e70b8","name":"","statusCode":"","headers":{},"x":600,"y":500,"wires":[]},{"id":"251dac8b.e40ad4","type":"ibmiot","name":"iotdata","keepalive":"60","serverName":"h1ka6y.messaging.internetofthings.ibmcloud.com ","cleansession":true,"appId":"","shared":false},{"id":"e94b4e9a.62a15","type":"ui_group","name":"Default","tab":"5e52ea52.44bae4","order":1,"disp":true,"width":"6","collapse":false},{"id":"5e52ea52.44bae4","type":"ui_tab","name":"Home","icon":"dashboard","disabled":false,"hidden":false}]